earthkit_data_demo_source/__init__.py
earthkit_data_demo_source/_version.py
earthkit_data_demo_source/demo.py
earthkit_data_demo_source/version.py
earthkit_data_demo_source-0.1.0.dist-info/LICENSE
earthkit_data_demo_source-0.1.0.dist-info/METADATA
earthkit_data_demo_source-0.1.0.dist-info/WHEEL
earthkit_data_demo_source-0.1.0.dist-info/entry_points.txt
earthkit_data_demo_source-0.1.0.dist-info/top_level.txt
earthkit_data_demo_source-0.1.0.dist-info/RECORD
